oracle_luau/__init__.py
oracle.luau-1.0.5.dist-info/LICENSE
oracle.luau-1.0.5.dist-info/METADATA
oracle.luau-1.0.5.dist-info/WHEEL
oracle.luau-1.0.5.dist-info/top_level.txt
oracle.luau-1.0.5.dist-info/RECORD
