Metadata-Version: 2.2
Name: oracle.luau
Version: 1.0.5
Summary: An API wrapper for the Oracle Luau decompiler.
Home-page: https://github.com/ActualMasterOogway/oracle.luau
Author: ActualMasterOogway
Author-email: ActualMasterOogway <realmasteroogway.contact@gmail.com>
License:                     GNU GENERAL PUBLIC LICENSE
Requires-Python: >=3.6
License-File: LICENSE
Dynamic: author
Dynamic: home-page
Dynamic: requires-python
